pokeyeh/__init__.py
pokeyeh/pokemon.csv
pokeyeh/random_pokemon.py
pokeyeh-1.0.1.dist-info/METADATA
pokeyeh-1.0.1.dist-info/WHEEL
pokeyeh-1.0.1.dist-info/top_level.txt
pokeyeh-1.0.1.dist-info/RECORD
